tspkg_base/__init__.py
tspkg_base/aop/__init__.py
tspkg_base/aop/context.py
tspkg_base/aop/decorators.py
tspkg_base/aop/injector.py
tspkg_base/aop/registry.py
tspkg_base/api/__init__.py
tspkg_base/api/fastapi_route_registry.py
tspkg_base/api/flask_blueprint_registry.py
tspkg_base/loader/__init__.py
tspkg_base/loader/security.py
tspkg_base/loader/tspkg_loader.py
tspkg_base/runtime/__init__.py
tspkg_base/runtime/bootstrap.py
tspkg_base/runtime/exception_handler.py
tspkg_base-0.1.8.dist-info/licenses/LICENSE
tspkg_base-0.1.8.dist-info/METADATA
tspkg_base-0.1.8.dist-info/WHEEL
tspkg_base-0.1.8.dist-info/top_level.txt
tspkg_base-0.1.8.dist-info/RECORD
